api/__init__.py
api/movie_api.py
api/quote_api.py
lotr_api_toolkit-0.1.0.dist-info/METADATA
lotr_api_toolkit-0.1.0.dist-info/WHEEL
lotr_api_toolkit-0.1.0.dist-info/top_level.txt
lotr_api_toolkit-0.1.0.dist-info/RECORD
